LICENSE
MANIFEST.in
README.md
setup.py
tap_adwords/__init__.py
tap_adwords.egg-info/PKG-INFO
tap_adwords.egg-info/SOURCES.txt
tap_adwords.egg-info/dependency_links.txt
tap_adwords.egg-info/entry_points.txt
tap_adwords.egg-info/requires.txt
tap_adwords.egg-info/top_level.txt
tap_adwords/metadata/accounts.json
tap_adwords/metadata/ad_groups.json
tap_adwords/metadata/ads.json
tap_adwords/metadata/campaigns.json
tap_adwords/schemas/accounts.json
tap_adwords/schemas/ad_groups.json
tap_adwords/schemas/ads.json
tap_adwords/schemas/campaigns.json