Metadata-Version: 2.1
Name: tap-adwords
Version: 1.11.0
Summary: Singer.io tap for extracting data from the Adwords api
Home-page: http://singer.io
Author: Stitch
License: UNKNOWN
Platform: UNKNOWN
Classifier: Programming Language :: Python :: 3 :: Only
Provides-Extra: dev
